appshell/__init__.py
appshell/apps.py
appshell/decorators.py
appshell/response.py
appshell/telepath.py
appshell/static/appshell/fonts/.gitignore
appshell/static/appshell/images/.gitignore
appshell/static/appshell/js/.gitignore
appshell/templates/appshell/bootstrap.html
appshell/test/__init__.py
appshell/test/apps.py
appshell/test/settings.py
appshell/test/urls.py
appshell/test/tests/__init__.py
appshell/ui/__init__.py
appshell/ui/forms.py
django_react_appshell-0.1.0.dist-info/LICENSE
django_react_appshell-0.1.0.dist-info/METADATA
django_react_appshell-0.1.0.dist-info/WHEEL
django_react_appshell-0.1.0.dist-info/top_level.txt
django_react_appshell-0.1.0.dist-info/RECORD
