Metadata-Version: 2.1
Name: django-react-appshell
Version: 0.1.0
Summary: A framework for building React SPA frontends for Django projects
Home-page: 
Author: Karl Hobley
Author-email: karl@kaed.uk
License: BSD
Classifier: Development Status :: 3 - Alpha
Classifier: Intended Audience :: Developers
Classifier: License :: OSI Approved :: BSD License
Classifier: Operating System :: OS Independent
Classifier: Programming Language :: Python
Classifier: Programming Language :: Python :: 3
Classifier: Programming Language :: Python :: 3.10
Classifier: Framework :: Django
Classifier: Framework :: Django :: 4.0
License-File: LICENSE
Requires-Dist: Django (<5.0,>=4.0)
Requires-Dist: telepath (<0.4,>=0.3)
Provides-Extra: dev
Requires-Dist: black (<23,>=22) ; extra == 'dev'
Requires-Dist: flake8 (<6,>=5) ; extra == 'dev'
Requires-Dist: isort (<6,>=5) ; extra == 'dev'
